cursor_snap/__init__.py
cursor_snap/cursor_snap.py
cursor_snap-2.1.0.dist-info/entry_points.txt
cursor_snap-2.1.0.dist-info/LICENSE
cursor_snap-2.1.0.dist-info/METADATA
cursor_snap-2.1.0.dist-info/WHEEL
cursor_snap-2.1.0.dist-info/RECORD
