Metadata-Version: 2.3
Name: cursor-snap
Version: 2.1.0
Summary: A utility tool to manage and reset Cursor Editor app IDs
License: MIT
Author: Adel Elawady
Author-email: adel50ali50@gmail.com
Requires-Python: >=3.6,<4.0
Classifier: License :: OSI Approved :: MIT License
Classifier: Programming Language :: Python :: 3
Classifier: Programming Language :: Python :: 3.6
Classifier: Programming Language :: Python :: 3.7
Classifier: Programming Language :: Python :: 3.8
Classifier: Programming Language :: Python :: 3.9
Classifier: Programming Language :: Python :: 3.10
Classifier: Programming Language :: Python :: 3.11
Classifier: Programming Language :: Python :: 3.12
Classifier: Programming Language :: Python :: 3.13
Requires-Dist: pathlib (>=1.0.1,<2.0.0)
Requires-Dist: rich (>=10.0.0,<11.0.0)
